anitakuapi/api.py
anitakuapi-1.0.0.dist-info/LICENSE
anitakuapi-1.0.0.dist-info/METADATA
anitakuapi-1.0.0.dist-info/WHEEL
anitakuapi-1.0.0.dist-info/top_level.txt
anitakuapi-1.0.0.dist-info/RECORD
