Metadata-Version: 2.1
Name: anitakuapi
Version: 1.0.0
Summary: Python wrapper for the Anitakuapi
Home-page: https://github.com/N-SUDY/AnitakuapiX
Author: zawlay
Author-email: zawlay134594@gmail.com
License: MIT
Keywords: API,AnitakuApi,Aniapi,Anibot,GogoAnime,Anime,AnimeAPI,Scrapper
License-File: LICENSE
Requires-Dist: requests
